{"id":25772,"path":"Assets/Prefabs/GetColorButton.prefab","assetBundleId":-1,"components":[{"type":2,"id":25784,"data":[0.5,0.5,0,0,0,0,160,160,0,0,0,0,0,0,1,1,1,1]},{"type":3,"id":25786,"data":[1]},{"type":4,"id":25788,"enabled":1,"class":5,"data":[6,25794,0,0,1,4,1,1,0,0,1,null,null,1,0.933962285518646,0,0,1,1,0,0,0,0]},{"type":4,"id":25790,"enabled":1,"class":8,"data":[[[[]]],[3,0,null,null,null,null,null,null,null,null],1,[1,1,1,1,0.960784316062927,0.960784316062927,0.960784316062927,1,0.7843137383461,0.7843137383461,0.7843137383461,1,0.960784316062927,0.960784316062927,0.960784316062927,1,0.7843137383461,0.7843137383461,0.7843137383461,0.501960813999176,1,0.100000001490116],[null,null,null,null,null,null,null,null],["Normal","Highlighted","Pressed","Selected","Disabled"],1,5,25788]},{"type":9,"id":25594,"enabled":1,"class":10,"data":[0,0,0,0,0,11,25774,5,25776,5,25778,5,25780,null,null]}],"children":[{"id":25802,"path":"Assets/Prefabs/GetColorButton.prefab","assetBundleId":-1,"components":[{"type":2,"id":25964,"data":[0.5,0.5,0,0,1,1,0,0,0,0,0,0,0,0,1,1,1,1]},{"type":3,"id":25976,"data":[1]},{"type":4,"id":25774,"enabled":1,"class":11,"data":[0,null,null,0,0,0,0,"1",0,12,25414,13,25416,[],null,null,[],0,0,0,255,0,0,0,1,0,3,[1,1,1,1,1,1,1,1,1,1,1,1,1,1,1,1],null,null,null,null,0,null,null,-1183493901,0,255,255,255,255,72,24,400,1,0,72,0,2,4096,65535,0,0,0,0,0,0,1,0.400000005960464,0,null,null,null,null,1,0,0,1,1,1,0,0,0,0,0,0,0,1,1,0,0,0,0,0,0,null,null,1,1,1,1,1,1,0,0,0,0]}],"children":[],"data":["Text (TMP)",0,1,0,5]},{"id":25792,"path":"Assets/Prefabs/GetColorButton.prefab","assetBundleId":-1,"components":[{"type":2,"id":25966,"data":[0.5,0.5,0.5,0.5,0.5,0.5,135,25,0,-56.1100006103516,0,0,0,0,1,1,1,1]},{"type":3,"id":25970,"data":[1]},{"type":4,"id":25776,"enabled":0,"class":5,"data":[6,25794,0,0,1,4,1,1,0,0,1,null,null,1,0,0,0,1,1,0,0,0,0]}],"children":[{"id":25796,"path":"Assets/Prefabs/GetColorButton.prefab","assetBundleId":-1,"components":[{"type":2,"id":25972,"data":[0.5,0.5,0.5,0.5,0.5,0.5,130,20,0,0,0,0,0,0,1,1,1,1]},{"type":3,"id":25974,"data":[1]},{"type":4,"id":25778,"enabled":0,"class":5,"data":[6,25794,3,0,1,0,0,1,0,0,1,null,null,1,1,0,0,1,1,0,0,0,0]}],"children":[],"data":["Fill",0,1,0,5]}],"data":["BackGround",0,1,0,5]},{"id":25798,"path":"Assets/Prefabs/GetColorButton.prefab","assetBundleId":-1,"components":[{"type":2,"id":25968,"data":[0.5,0.5,0,0,1,1,0,0,0,0,0,0,0,0,1,1,1,1]},{"type":3,"id":25978,"data":[1]},{"type":4,"id":25780,"enabled":0,"class":5,"data":[6,25800,0,0,1,4,1,1,0,0,1,null,null,1,1,1,1,1,1,0,0,0,0]}],"children":[],"data":["TickComplete",0,1,0,5]}],"data":["GetColorButton",0,1,0,5]}